actioncable/__init__.py
actioncable/consumer.py
actioncable/registry.py
actioncable/utils.py
django_actioncable-1.0.4.dist-info/METADATA
django_actioncable-1.0.4.dist-info/WHEEL
django_actioncable-1.0.4.dist-info/RECORD
