Metadata-Version: 2.1
Name: django-actioncable
Version: 1.0.4
Summary: This package provides Rails Action Cable support to Django
Home-page: https://github.com/AccordBox/django-actioncable
License: MIT
Author: Michael Yin
Author-email: michaelyin@accordbox.com
Requires-Python: >=3.8
Classifier: License :: OSI Approved :: MIT License
Classifier: Programming Language :: Python :: 3
Classifier: Programming Language :: Python :: 3.8
Classifier: Programming Language :: Python :: 3.9
Classifier: Programming Language :: Python :: 3.10
Classifier: Programming Language :: Python :: 3.11
Classifier: Programming Language :: Python :: 3.12
Requires-Dist: channels (>=3.0)
Requires-Dist: django (>=3.0)
Project-URL: Changelog, https://github.com/AccordBox/django-actioncable/releases
